Metadata-Version: 2.3
Name: mseep-skyvern
Version: 0.2.5
Summary: 
Author: mseep
Author-email: support@skydeck.ai
Maintainer: mseep
Maintainer-email: support@skydeck.ai
Requires-Python: >=3.11,<3.14
Classifier: Programming Language :: Python :: 3
Classifier: Programming Language :: Python :: 3.11
Classifier: Programming Language :: Python :: 3.12
Classifier: Programming Language :: Python :: 3.13
Requires-Dist: aioboto3 (>=14.3.0,<15.0.0)
Requires-Dist: aiofiles (>=24.1.0,<25.0.0)
Requires-Dist: aiohttp (>=3.8.5,<4.0.0)
Requires-Dist: aioredlock (>=0.7.3,<0.8.0)
Requires-Dist: alembic (>=1.12.1,<2.0.0)
Requires-Dist: alive-progress (>=3.2.0,<4.0.0)
Requires-Dist: anthropic (>=0.50.0,<0.51.0)
Requires-Dist: asyncache (>=0.3.1,<0.4.0)
Requires-Dist: asyncpg (>=0.30.0,<0.31.0)
Requires-Dist: cachetools (>=5.3.2,<6.0.0)
Requires-Dist: colorama (>=0.4.6,<0.5.0)
Requires-Dist: curlparser (>=0.1.0,<0.2.0)
Requires-Dist: ddtrace (>=2.3.2,<3.0.0)
Requires-Dist: email-validator (>=2.2.0,<3.0.0)
Requires-Dist: fastapi (>=0.115.4,<0.116.0)
Requires-Dist: fastmcp (>=2.10.1,<3.0.0)
Requires-Dist: filetype (>=1.2.0,<2.0.0)
Requires-Dist: google-cloud-aiplatform (>=1.90.0,<2.0.0)
Requires-Dist: greenlet (==3.0.3) ; python_version == "3.11"
Requires-Dist: greenlet (>3.0.3) ; python_version >= "3.12" and python_version < "3.14"
Requires-Dist: httpx[socks] (>=0.27.0)
Requires-Dist: jinja2 (>=3.1.2,<4.0.0)
Requires-Dist: json-repair (>=0.34.0,<0.35.0)
Requires-Dist: lark (>=1.2.2,<2.0.0)
Requires-Dist: libcst (>=1.8.2,<2.0.0)
Requires-Dist: litellm (>=1.73.6)
Requires-Dist: lmnr[all] (>=0.6.16,<0.7.0)
Requires-Dist: onepassword-sdk (==0.3.0)
Requires-Dist: onnxruntime (<1.17) ; python_version == "3.11"
Requires-Dist: onnxruntime (>=1.20.0,<1.23.0) ; python_version >= "3.12" and python_version < "3.14"
Requires-Dist: openai (>=1.68.2)
Requires-Dist: orjson (>=3.9.10,<4.0.0)
Requires-Dist: pillow (>=10.1.0,<11.0.0)
Requires-Dist: playwright (==1.46.0) ; python_version == "3.11"
Requires-Dist: playwright (>1.46.0) ; python_version >= "3.12" and python_version < "3.14"
Requires-Dist: posthog (>=3.7.0,<4.0.0)
Requires-Dist: psutil (>=7.0.0)
Requires-Dist: psycopg[binary,pool] (==3.1.18) ; python_version >= "3.11" and python_version < "3.13"
Requires-Dist: psycopg[binary,pool] (>=3.2.2,<3.3.0) ; python_version == "3.13"
Requires-Dist: pydantic (>=2.5.2,<3.0.0)
Requires-Dist: pydantic-settings (>=2.1.0,<3.0.0)
Requires-Dist: pyotp (>=2.9.0,<3.0.0)
Requires-Dist: pypdf (>=5.1.0,<6.0.0)
Requires-Dist: python-dotenv (>=1.0.0,<2.0.0)
Requires-Dist: python-jose[cryptography] (>=3.4.0,<4.0.0)
Requires-Dist: python-multipart (>=0.0.18,<0.0.19)
Requires-Dist: redis (>=5.0.3,<6.0.0)
Requires-Dist: requests-toolbelt (>=1.0.0,<2.0.0)
Requires-Dist: rich[jupyter] (>=13.7.0,<14.0.0)
Requires-Dist: sqlalchemy[mypy] (>=2.0.29,<3.0.0)
Requires-Dist: starlette-context (>=0.3.6,<0.4.0)
Requires-Dist: stripe (>=9.7.0,<10.0.0)
Requires-Dist: structlog (>=23.2.0,<24.0.0)
Requires-Dist: temporalio (>=1.6.0,<2.0.0)
Requires-Dist: tiktoken (>=0.9.0)
Requires-Dist: tldextract (>=5.1.2,<6.0.0)
Requires-Dist: toml (>=0.10.2,<0.11.0)
Requires-Dist: typer (>=0.16.0)
Requires-Dist: types-boto3[full] (>=1.38.31,<2.0.0)
Requires-Dist: types-toml (>=0.10.8.7,<0.11.0.0)
Requires-Dist: uvicorn[standard] (>=0.24.0.post1,<0.25.0)
Requires-Dist: websockets (>=12.0,<13.0)
